{
  "did": "did:plc:hlchta7bwmobyum375ltycg5",
  "time_us": 1776026537696658,
  "kind": "commit",
  "commit": {
    "rev": "3mjd7ni4k2o23",
    "operation": "create",
    "collection": "network.cosmik.collectionLink",
    "rkey": "3mjd7ni2jm623",
    "record": {
      "$type": "network.cosmik.collectionLink",
      "addedAt": "2026-04-12T20:42:17.173Z",
      "addedBy": "did:plc:hlchta7bwmobyum375ltycg5",
      "card": {
        "cid": "bafyreiek5l5smjuucp3dejvnd6wvwgbfn2l7a2rxhxm6bm4ojerlm3fvg4",
        "uri": "at://did:plc:hlchta7bwmobyum375ltycg5/network.cosmik.card/3mjd7ngos4p2m"
      },
      "collection": {
        "cid": "bafyreibk3sqvmzfv2yyhlwfps6no2ppsa52qwviyzqysz2clxfgbijdjre",
        "uri": "at://did:plc:hlchta7bwmobyum375ltycg5/network.cosmik.collection/3mjd5t5a2mf2v"
      },
      "createdAt": "2026-04-12T20:42:17.273Z"
    },
    "cid": "bafyreiffhisszsvf5sy4abuxt2yup7i5ltaoysqgpf7o46xqz4uy3fekxu"
  }
}