{
  "did": "did:plc:hlchta7bwmobyum375ltycg5",
  "time_us": 1732396324819,
  "kind": "commit",
  "commit": {
    "uri": "at://did:plc:hlchta7bwmobyum375ltycg5/app.bsky.feed.post/3lbnftsu54k2o",
    "collection": "app.bsky.feed.post",
    "rkey": "3lbnftsu54k2o",
    "record": {
      "text": "If anyone fluent in #Klingon and passable with #PowerShell functions wants to make a fun #StarTrek module with me, DM me.  \n\n#Qapla !",
      "$type": "app.bsky.feed.post",
      "langs": [
        "en"
      ],
      "reply": {
        "root": {
          "cid": "bafyreig2ypoz4mr6xusne34udueiqj4ixwbppv2oyraiixa2erpw7ihtey",
          "uri": "at://did:plc:lmuflauez6nvcvshbl2dvisr/app.bsky.feed.post/3lbljetvdk22e"
        },
        "parent": {
          "cid": "bafyreibcg6zwilk56zqeegnhg3koupvu66owj6ux7pv3xhktg2bopxi4nq",
          "uri": "at://did:plc:3553clysritaplsofpzgegrj/app.bsky.feed.post/3lbmmk4zh722d"
        }
      },
      "facets": [
        {
          "index": {
            "byteEnd": 28,
            "byteStart": 20
          },
          "features": [
            {
              "tag": "Klingon",
              "$type": "app.bsky.richtext.facet#tag"
            }
          ]
        },
        {
          "index": {
            "byteEnd": 58,
            "byteStart": 47
          },
          "features": [
            {
              "tag": "PowerShell",
              "$type": "app.bsky.richtext.facet#tag"
            }
          ]
        },
        {
          "index": {
            "byteEnd": 98,
            "byteStart": 89
          },
          "features": [
            {
              "tag": "StarTrek",
              "$type": "app.bsky.richtext.facet#tag"
            }
          ]
        },
        {
          "index": {
            "byteEnd": 131,
            "byteStart": 125
          },
          "features": [
            {
              "tag": "Qapla",
              "$type": "app.bsky.richtext.facet#tag"
            }
          ]
        }
      ],
      "createdAt": "2024-11-23T21:12:04.819Z"
    },
    "cid": "bafyreihnxmuzewxgzohbbsy45njxzd5trbzk3kbwcjkawetqm26o6j6nfq"
  }
}