{
  "did": "did:plc:hlchta7bwmobyum375ltycg5",
  "time_us": 1735509094952,
  "kind": "commit",
  "commit": {
    "uri": "at://did:plc:hlchta7bwmobyum375ltycg5/app.bsky.feed.post/3lehytltnqk2s",
    "collection": "app.bsky.feed.post",
    "rkey": "3lehytltnqk2s",
    "record": {
      "text": "Apparently someone parkour'd into my building and stole holiday packages and mail, including ( possibly ) my ID.\n\nI guess #PorchPirates are now #ninjas, too.\n\n#TisTheSeason #Seattle #FML #Crime #CityLife\n\nIf you know this person, reach out.\n\nIf you are this person, what is wrong with you?",
      "$type": "app.bsky.feed.post",
      "embed": {
        "$type": "app.bsky.embed.images",
        "images": [
          {
            "alt": "Some parkour / ninja porch pirate steals some packages at 5 in the morning the weekend after Christmas.",
            "image": {
              "$type": "blob",
              "ref": {
                "$link": "bafkreiasbjldkkpxrubt3stuqemrfk2t27kd764q5jfratk7lgilskps4u"
              },
              "mimeType": "image/jpeg",
              "size": 754084
            },
            "aspectRatio": {
              "width": 2000,
              "height": 1200
            }
          }
        ]
      },
      "langs": [
        "en"
      ],
      "facets": [
        {
          "index": {
            "byteEnd": 135,
            "byteStart": 122
          },
          "features": [
            {
              "tag": "PorchPirates",
              "$type": "app.bsky.richtext.facet#tag"
            }
          ]
        },
        {
          "index": {
            "byteEnd": 151,
            "byteStart": 144
          },
          "features": [
            {
              "tag": "ninjas",
              "$type": "app.bsky.richtext.facet#tag"
            }
          ]
        },
        {
          "index": {
            "byteEnd": 172,
            "byteStart": 159
          },
          "features": [
            {
              "tag": "TisTheSeason",
              "$type": "app.bsky.richtext.facet#tag"
            }
          ]
        },
        {
          "index": {
            "byteEnd": 181,
            "byteStart": 173
          },
          "features": [
            {
              "tag": "Seattle",
              "$type": "app.bsky.richtext.facet#tag"
            }
          ]
        },
        {
          "index": {
            "byteEnd": 186,
            "byteStart": 182
          },
          "features": [
            {
              "tag": "FML",
              "$type": "app.bsky.richtext.facet#tag"
            }
          ]
        },
        {
          "index": {
            "byteEnd": 193,
            "byteStart": 187
          },
          "features": [
            {
              "tag": "Crime",
              "$type": "app.bsky.richtext.facet#tag"
            }
          ]
        },
        {
          "index": {
            "byteEnd": 203,
            "byteStart": 194
          },
          "features": [
            {
              "tag": "CityLife",
              "$type": "app.bsky.richtext.facet#tag"
            }
          ]
        }
      ],
      "createdAt": "2024-12-29T21:51:34.952Z"
    },
    "cid": "bafyreibs4bvu4yctndjgte6ofagnccmbhokcxowsq4dkivllqe3sho7hvy"
  }
}