{
  "did": "did:plc:hlchta7bwmobyum375ltycg5",
  "time_us": 1740527823883,
  "kind": "commit",
  "commit": {
    "uri": "at://did:plc:hlchta7bwmobyum375ltycg5/app.bsky.feed.post/3lj22veo6qc2w",
    "collection": "app.bsky.feed.post",
    "rkey": "3lj22veo6qc2w",
    "record": {
      "text": "I was figuring this would be a bit more frantic, but now I'm just wondering if Infected Mushroom stopped hiring good video directors.\n\nyoutu.be/Z6hL6fkJ1_k?...\n\nAh well, at least this track is more apt for our times ( even if it's old )",
      "$type": "app.bsky.feed.post",
      "embed": {
        "$type": "app.bsky.embed.external",
        "external": {
          "uri": "https://youtu.be/Z6hL6fkJ1_k?si=r_pDqV03VkHQcXrC",
          "thumb": {
            "$type": "blob",
            "ref": {
              "$link": "bafkreihghvfl2ipyandhpuacvv4w45e3lf3okrrq3ii7esfp2hpskgzh2m"
            },
            "mimeType": "image/jpeg",
            "size": 25959
          },
          "title": "Infected Mushroom - Becoming Insane",
          "description": "YouTube video by kraudio"
        }
      },
      "langs": [
        "en"
      ],
      "reply": {
        "root": {
          "cid": "bafyreieb32u3wp5vndg3eviatyrwtrtwmm4hvo5reyw4wbmhk4qrbkfhjm",
          "uri": "at://did:plc:bpmtx4nv56gasrya66xwxigw/app.bsky.feed.post/3liznfm3h5c2m"
        },
        "parent": {
          "cid": "bafyreigflczghszhm5ye5e33le6xkj3yi4wf3pl74rppbazjerg6jgihue",
          "uri": "at://did:plc:bpmtx4nv56gasrya66xwxigw/app.bsky.feed.post/3lj22rofr6c22"
        }
      },
      "facets": [
        {
          "index": {
            "byteEnd": 159,
            "byteStart": 135
          },
          "features": [
            {
              "uri": "https://youtu.be/Z6hL6fkJ1_k?si=r_pDqV03VkHQcXrC",
              "$type": "app.bsky.richtext.facet#link"
            }
          ]
        }
      ],
      "createdAt": "2025-02-25T23:57:03.883Z"
    },
    "cid": "bafyreielvpqtf5xnho4rtpplaxkzrr7iinph5dfapmcnodgwcmk64wipcm"
  }
}