{
  "did": "did:plc:hlchta7bwmobyum375ltycg5",
  "time_us": 1741906994056,
  "kind": "commit",
  "commit": {
    "uri": "at://did:plc:hlchta7bwmobyum375ltycg5/app.bsky.feed.post/3lkc7dttmu22n",
    "collection": "app.bsky.feed.post",
    "rkey": "3lkc7dttmu22n",
    "record": {
      "text": "BetterHelp really will put an ad anywhere, won't they ?",
      "$type": "app.bsky.feed.post",
      "langs": [
        "en"
      ],
      "reply": {
        "root": {
          "cid": "bafyreiegewmvaezuyvarnuvfwa2izbzy5nerivg2atu56recftrin5rg6a",
          "uri": "at://did:plc:j25ig3ar6gigewdmk47fzwpd/app.bsky.feed.post/3lkbmtfjndc2o"
        },
        "parent": {
          "cid": "bafyreiegewmvaezuyvarnuvfwa2izbzy5nerivg2atu56recftrin5rg6a",
          "uri": "at://did:plc:j25ig3ar6gigewdmk47fzwpd/app.bsky.feed.post/3lkbmtfjndc2o"
        }
      },
      "createdAt": "2025-03-13T23:03:14.056Z"
    },
    "cid": "bafyreie47s22qjb3pnctfc635ojfr2r7xusr6f7hsljmm4dq57wntf76ny"
  }
}