{
  "did": "did:plc:hlchta7bwmobyum375ltycg5",
  "time_us": 1745601605759945,
  "kind": "commit",
  "commit": {
    "rev": "3lnnq7r2v2s2v",
    "operation": "create",
    "collection": "app.bsky.feed.post",
    "rkey": "3lnnq7si4mc25",
    "record": {
      "$type": "app.bsky.feed.post",
      "createdAt": "2025-04-25T17:20:04.028Z",
      "facets": [
        {
          "$type": "app.bsky.richtext.facet",
          "features": [
            {
              "$type": "app.bsky.richtext.facet#mention",
              "did": "did:plc:mw5tp66tuni2c2afhyxcyc5g"
            }
          ],
          "index": {
            "byteEnd": 30,
            "byteStart": 10
          }
        }
      ],
      "langs": [
        "en"
      ],
      "reply": {
        "parent": {
          "cid": "bafyreieomb6ndvmkeazvso3opgzshyoypn53vrp7aw63pyxzyjcepcej6y",
          "uri": "at://did:plc:rlrrzgcyzronxjjnzorjmdeb/app.bsky.feed.post/3lnnbl4in2s25"
        },
        "root": {
          "cid": "bafyreieomb6ndvmkeazvso3opgzshyoypn53vrp7aw63pyxzyjcepcej6y",
          "uri": "at://did:plc:rlrrzgcyzronxjjnzorjmdeb/app.bsky.feed.post/3lnnbl4in2s25"
        }
      },
      "text": "I believe @deactv8.bsky.social is working on something that might help.\n\nIf not, I'm happy to help make something.\n\nWhat are you trying to test?\n\n(DM if you want to get into the weeds)"
    },
    "cid": "bafyreicv2txouzqk33nx4rv7am52mm7lwonqhajhhzbavhbktpmyizmjum"
  }
}