{
  "did": "did:plc:hlchta7bwmobyum375ltycg5",
  "time_us": 1768452980253129,
  "kind": "commit",
  "commit": {
    "rev": "3mcgs7uxicy2p",
    "operation": "create",
    "collection": "app.bsky.feed.post",
    "rkey": "3mcgs7v5btk2z",
    "record": {
      "$type": "app.bsky.feed.post",
      "createdAt": "2026-01-15T04:56:20.319Z",
      "langs": [
        "en"
      ],
      "reply": {
        "parent": {
          "cid": "bafyreifvejzk6etf33idkhazvps3eyxc6ylm2xskcvru6rtlx5wzds6kce",
          "uri": "at://did:plc:waaktpm6r63m5frsf7itvkjn/app.bsky.feed.post/3mcgr57wyhc22"
        },
        "root": {
          "cid": "bafyreihxmfqupgezobm5ugkgxsyzgoxzzsfueyvxj4fplu3i26mceanza4",
          "uri": "at://did:plc:6hakn4o42hz5mffdlofynjiy/app.bsky.feed.post/3mcfbs72evs2e"
        }
      },
      "text": "RunspacePools are *almost* just a pool or runspaces ( we debated this for about a year, and I wish that what you said was more true from an api perspective ).\n\nRunspacePools are \"lighter\" to keep constructing.  They queue instead of fail when there's more than one thing to do.   And they flex."
    },
    "cid": "bafyreihxzlwds3rffbsrg2j43ygohdryuithydlgdqthbwinzgrdvxth6q"
  }
}