{
  "did": "did:plc:hlchta7bwmobyum375ltycg5",
  "time_us": 1775600932355329,
  "kind": "commit",
  "commit": {
    "rev": "3miwtbhag4s24",
    "operation": "create",
    "collection": "app.bsky.feed.post",
    "rkey": "3miwtafsgys2s",
    "record": {
      "$type": "app.bsky.feed.post",
      "createdAt": "2026-04-07T22:28:17.112Z",
      "langs": [
        "en"
      ],
      "reply": {
        "parent": {
          "cid": "bafyreiffasroqbhlwt62pr4yfozip7r6cugvx63f7whoqz732j5qqck34e",
          "uri": "at://did:plc:6zhplfrjlzylwhoou3po4jkk/app.bsky.feed.post/3miws2upqts23"
        },
        "root": {
          "cid": "bafyreicwhazbqll5kmzscrb6ahj5p2fwm3cnrmjoetk6hjhyqzxcxqo6aq",
          "uri": "at://did:plc:6zhplfrjlzylwhoou3po4jkk/app.bsky.feed.post/3miwro55o622i"
        }
      },
      "text": "What did it do?\n\n(even us experts have a love/hate with our languages of choice)"
    },
    "cid": "bafyreiahwrbrde2z5jgvsvs43i5v2jkj7ljjewhteypmmcr6tyo7ezc3zu"
  }
}