{
  "did": "did:plc:hlchta7bwmobyum375ltycg5",
  "time_us": 1747614778293333,
  "kind": "commit",
  "commit": {
    "rev": "3lpid52uerj23",
    "operation": "create",
    "collection": "app.bsky.feed.like",
    "rkey": "3lpid52u5wr23",
    "record": {
      "$type": "app.bsky.feed.like",
      "createdAt": "2025-05-19T00:32:58.637Z",
      "subject": {
        "cid": "bafyreif35khvu5dli4lacpghdjkafc33a4o26kyqgueph7necbo5k4b63e",
        "uri": "at://did:plc:uwe6qbcbuumnz4kke33qqwi2/app.bsky.feed.post/3lpi7rwmy3s2w"
      }
    },
    "cid": "bafyreibwhy2nxaglum4ethuq3wnubkubprmvyeesd7eqkar3b3erlhe25i"
  }
}