{
  "did": "did:plc:hlchta7bwmobyum375ltycg5",
  "time_us": 1747967178019348,
  "kind": "commit",
  "commit": {
    "rev": "3lpsldfiatj2k",
    "operation": "create",
    "collection": "app.bsky.feed.like",
    "rkey": "3lpsldfhqab2k",
    "record": {
      "$type": "app.bsky.feed.like",
      "createdAt": "2025-05-23T02:26:20.5Z",
      "subject": {
        "cid": "bafyreiem7uamdvgwtqmqrb56fghwn6j2q3wwawpos7jhjrmbqywzyybwym",
        "uri": "at://did:plc:dq6jaefxy6vc6vvthg57kwvs/app.bsky.feed.post/3lpsishsa6c2g"
      }
    },
    "cid": "bafyreibvlnil756johhbnogvh52nea4etzwbm7cgqqpa2phvfol47dnpzi"
  }
}