{
  "did": "did:plc:hlchta7bwmobyum375ltycg5",
  "time_us": 1770840878801788,
  "kind": "commit",
  "commit": {
    "rev": "3memc4shcab23",
    "operation": "create",
    "collection": "app.bsky.feed.like",
    "rkey": "3memc4sgzgz23",
    "record": {
      "$type": "app.bsky.feed.like",
      "createdAt": "2026-02-11T20:14:38.559Z",
      "subject": {
        "cid": "bafyreidfmhlogbsfw2y2ei5d6iuvmcmehtxa3wc3oagkis6yomm2h3fc6u",
        "uri": "at://did:plc:eudjwpx7av6t5kbha4faa5ab/app.bsky.feed.post/3mem44xrtks2x"
      }
    },
    "cid": "bafyreidweufapjo6h5mbjrblvoybbjo5tqcx32ymos4pqtcw7kdlutsyqq"
  }
}