{
  "did": "did:plc:hlchta7bwmobyum375ltycg5",
  "time_us": 1772053140359657,
  "kind": "commit",
  "commit": {
    "rev": "3mfpl4yx4sn2d",
    "operation": "create",
    "collection": "app.bsky.feed.like",
    "rkey": "3mfpl4ywt252d",
    "record": {
      "$type": "app.bsky.feed.like",
      "createdAt": "2026-02-25T20:59:01.707Z",
      "subject": {
        "cid": "bafyreidrzy635fn66bqoqlvjst62ytoxqfiitvsn6im5jssev7nirnfbim",
        "uri": "at://did:plc:uyymqbvrgg4bbxozoaqcvm6p/app.bsky.feed.post/3mfphnohmcs2z"
      }
    },
    "cid": "bafyreigqk3zflu2n76esfu6t5hehnwlhhgx2oy4gy6ksfw7n3ptafbc554"
  }
}