{
  "did": "did:plc:hlchta7bwmobyum375ltycg5",
  "time_us": 1776622617653399,
  "kind": "commit",
  "commit": {
    "rev": "3mjuks2bxre23",
    "operation": "create",
    "collection": "app.bsky.feed.like",
    "rkey": "3mjuks2aeye23",
    "record": {
      "$type": "app.bsky.feed.like",
      "createdAt": "2026-04-19T18:16:57.19Z",
      "subject": {
        "cid": "bafyreihyniilds3p2dyi6flifrbvlx2nfy4mbc6o2hivad6yr5ek4jfdjm",
        "uri": "at://did:plc:w4xbfzo7kqfes5zb7r6qv3rw/app.bsky.feed.post/3mju3yqxwss27"
      }
    },
    "cid": "bafyreiewqml4b54o6iheshlqg5setlsbmxhgncczmuoyh42lshxbbvjwuu"
  }
}